filesharing/.DS_Store
filesharing/__init__.py
filesharing/app.py
filesharing/build/.DS_Store
filesharing/common/globals.py
filesharing/common/logger.py
filesharing/common/read_credentials.py
filesharing/db/mongodbDAL.py
filesharing/domains/base_model_.py
filesharing/domains/request.py
filesharing/hook-shiboken2.py
filesharing/resources/credentials.json
filesharing/resources/number_of_checks.txt
filesharing/resources/port.txt
filesharing/resources/service_started_time.json
filesharing/screens/login.py
filesharing/utils/current_time.py
filesharing/utils/notifications.py
filesharing/utils/port.py
filesharing-0.1.0.dist-info/WHEEL
filesharing-0.1.0.dist-info/METADATA
filesharing-0.1.0.dist-info/RECORD
