Metadata-Version: 2.1
Name: filesharing
Version: 0.1.0
Summary: 
Author: YCipriani
Author-email: yonatancipriani@outlook.com
Requires-Python: >=3.9,<4.0
Classifier: Programming Language :: Python :: 3
Classifier: Programming Language :: Python :: 3.9
Requires-Dist: Flask (>=2.0.1,<3.0.0)
Requires-Dist: Flask-RESTful (>=0.3.9,<0.4.0)
Requires-Dist: black (>=21.7b0,<22.0)
Requires-Dist: colorlog (>=5.0.1,<6.0.0)
Requires-Dist: dnspython (>=2.1.0,<3.0.0)
Requires-Dist: pip (>=21.2.4,<22.0.0)
Requires-Dist: pyinstaller (>=4.5.1,<5.0.0)
Requires-Dist: pymongo (>=3.12.0,<4.0.0)
Requires-Dist: requests (>=2.26.0,<3.0.0)
